pyaug/__init__.py
pyaug-0.1.5.2.dist-info/LICENSE.txt
pyaug-0.1.5.2.dist-info/METADATA
pyaug-0.1.5.2.dist-info/WHEEL
pyaug-0.1.5.2.dist-info/top_level.txt
pyaug-0.1.5.2.dist-info/RECORD
