Metadata-Version: 2.1
Name: pyaug
Version: 0.1.5.2
Summary: A library which generates augmented data through perturbing Pandas DataFrames.
Home-page: https://github.com/pyaug/pyaug
Author: Joshua David Wood
Author-email: pyaugment@gmail.com
License: UNKNOWN
Platform: UNKNOWN
Classifier: Programming Language :: Python :: 3
Classifier: License :: OSI Approved :: MIT License
Classifier: Operating System :: OS Independent
